sfts/__init__.py
sfts/ansaetze.py
sfts/iphenot.py
sfts/kernels.py
sfts/taylor_t3.py
sfts-0.2.0.dist-info/LICENSE.md
sfts-0.2.0.dist-info/METADATA
sfts-0.2.0.dist-info/WHEEL
sfts-0.2.0.dist-info/top_level.txt
sfts-0.2.0.dist-info/RECORD
