Metadata-Version: 2.2
Name: sfts
Version: 0.2.0
Summary: Scalable data-analysis framework for long-duration gravitational-wave signals
Author-email: Rodrigo Tenorio <rodrigo.tenorio.marquez@gmail.com>
License: MIT License
Project-URL: Source, https://github.com/Rodrigo-Tenorio/sfts
Project-URL: Issue tracker, https://github.com/Rodrigo-Tenorio/sfts/issues
Classifier: Programming Language :: Python :: 3
Classifier: License :: OSI Approved :: MIT License
Classifier: Operating System :: OS Independent
Classifier: Natural Language :: English
Classifier: Intended Audience :: Science/Research
Requires-Python: >=3.12
License-File: LICENSE.md
Requires-Dist: jax
Requires-Dist: jaxopt
Provides-Extra: cuda
Requires-Dist: jax[cuda12]; extra == "cuda"
